{
  "6436b809621f5ab5d1b5e7e5": {
    "_id": "6436b809621f5ab5d1b5e7e5",
    "createdAt": 1681307657551,
    "updatedAt": 1681811705599,
    "count": 7,
    "name": "Templates",
    "forId": "templates"
  },
  "6436b899621f5ab5d1b5e7e7": {
    "_id": "6436b899621f5ab5d1b5e7e7",
    "createdAt": 1681307801577,
    "updatedAt": 1681811862128,
    "count": 23,
    "name": "Entries",
    "forId": "entries"
  },
  "6436c090621f5ab5d1b5e7ec": {
    "_id": "6436c090621f5ab5d1b5e7ec",
    "createdAt": 1681309840386,
    "updatedAt": 1694010851636,
    "count": 7,
    "name": "Groups",
    "forId": "groups"
  }
}